{
    "extend":".connection.base",
    "class":true,
    "constructor":false,
    "methods":[
        {
            "name":"acceptMessage",
            "impl":".connection.accept"
        },
        {
            "name":"isSubscribed",
            "impl":".connection.subscribed"
        },
        {
            "name":"subscribeOnce",
            "impl":".connection.subscribe.once"
        },
        {
            "name":"findOpenedSubscriberByName",
            "impl":".connection.find.subscriber.opened.name"
        },
        "subscribe",
        "unsubscribe",
        "subscribes",
        "unsubscribes",
        "activate",
        "deactivate"
    ]
}